itests/__init__.py
itests/tests/__init__.py
itests/tests/conftest.py
itests/tests/test_squeak_node.py
itests/tests/util.py
proto/__init__.py
squeaknode/__init__.py
squeaknode/main.py
squeaknode/admin/__init__.py
squeaknode/admin/icon.png
squeaknode/admin/messages.py
squeaknode/admin/profile_image_util.py
squeaknode/admin/squeak_admin_server_handler.py
squeaknode/admin/squeak_admin_server_servicer.py
squeaknode/admin/webapp/__init__.py
squeaknode/admin/webapp/app.py
squeaknode/admin/webapp/forms.py
squeaknode/admin/webapp/user.py
squeaknode/admin/webapp/static/build/_redirects
squeaknode/admin/webapp/static/build/asset-manifest.json
squeaknode/admin/webapp/static/build/favicon.ico
squeaknode/admin/webapp/static/build/index.html
squeaknode/admin/webapp/static/build/manifest.json
squeaknode/admin/webapp/static/build/robots.txt
squeaknode/admin/webapp/static/build/assets/css/bootstrap.min.css
squeaknode/admin/webapp/static/build/assets/css/ionicons.min.css
squeaknode/admin/webapp/static/build/assets/css/login.css
squeaknode/admin/webapp/static/build/assets/images/icon.png
squeaknode/admin/webapp/static/build/assets/js/bootstrap.bundle.min.js
squeaknode/admin/webapp/static/build/assets/js/jquery.min.js
squeaknode/admin/webapp/static/build/static/css/306.7f7715a0.chunk.css
squeaknode/admin/webapp/static/build/static/css/306.7f7715a0.chunk.css.map
squeaknode/admin/webapp/static/build/static/css/841.693c3c31.chunk.css
squeaknode/admin/webapp/static/build/static/css/841.693c3c31.chunk.css.map
squeaknode/admin/webapp/static/build/static/css/900.5027b0a1.chunk.css
squeaknode/admin/webapp/static/build/static/css/900.5027b0a1.chunk.css.map
squeaknode/admin/webapp/static/build/static/css/main.fe6c5463.css
squeaknode/admin/webapp/static/build/static/css/main.fe6c5463.css.map
squeaknode/admin/webapp/static/build/static/js/306.90b2a66c.chunk.js
squeaknode/admin/webapp/static/build/static/js/306.90b2a66c.chunk.js.map
squeaknode-0.3.5.dist-info/LICENSE
squeaknode-0.3.5.dist-info/METADATA
squeaknode-0.3.5.dist-info/WHEEL
squeaknode-0.3.5.dist-info/entry_points.txt
squeaknode-0.3.5.dist-info/top_level.txt
squeaknode-0.3.5.dist-info/RECORD
