Metadata-Version: 2.1
Name: squeaknode
Version: 0.3.5
Summary: Node for squeak protocol
Home-page: https://github.com/yzernik/squeaknode
Author: Jonathan Zernik
License: UNKNOWN
Platform: UNKNOWN
License-File: LICENSE
Requires-Dist: alembic (==1.7.1)
Requires-Dist: docutils (==0.17.1)
Requires-Dist: Flask (==2.0.1)
Requires-Dist: flask-cors (==3.0.10)
Requires-Dist: flask-login (==0.5.0)
Requires-Dist: Flask-WTF (==0.15.1)
Requires-Dist: googleapis-common-protos (==1.53.0)
Requires-Dist: importlib-resources (==1.4.0)
Requires-Dist: mypy-protobuf (==2.9)
Requires-Dist: protobuf (==3.17.3)
Requires-Dist: pyln-client (==0.10.1)
Requires-Dist: PySocks (==1.7.1)
Requires-Dist: python-bitcoinlib (==0.11.0)
Requires-Dist: pyzmq (==22.3.0)
Requires-Dist: requests[socks] (==2.26.0)
Requires-Dist: SQLAlchemy (==1.4.25)
Requires-Dist: squeaklib (==0.13.1)
Requires-Dist: typed-config (==0.2.5)
Requires-Dist: Werkzeug (==2.0.3)
Provides-Extra: postgres
Requires-Dist: psycopg2 ; extra == 'postgres'
Provides-Extra: test
Requires-Dist: pytest ; extra == 'test'
Requires-Dist: coverage ; extra == 'test'
